<?xml version="1.0" encoding="UTF-8" standalone="no"?><elencoGerarchie><gerarchia><radice><nome>rad</nome><campo>cam</campo><dominio><valoreDominio><valore>val</valore><descrizione>des</descrizione></valoreDominio><valoreDominio><valore>val2</valore><descrizione>Assente</descrizione></valoreDominio></dominio><categoria><nome>fog</nome><radice>rad</radice><valoreDominio><valore>val</valore><descrizione>des</descrizione></valoreDominio></categoria><categoria><nome>nonfog2</nome><campo>cam2</campo><dominio><valoreDominio><valore>val3</valore><descrizione>Assente</descrizione></valoreDominio></dominio><radice>rad</radice><valoreDominio><valore>val3</valore><descrizione>Assente</descrizione></valoreDominio><categoria><nome>fog3</nome><radice>rad</radice><valoreDominio><valore>val3</valore><descrizione>Assente</descrizione></valoreDominio></categoria></categoria></radice></gerarchia></elencoGerarchie>